galapy_core/__init__.py
galapy_core/accounts.py
galapy_core/assets.py
galapy_core/core.py
galapy_core/generators.py
galapy_core/handlers.py
galapy_core/market_data.py
galapy_core/metrics.py
galapy_core/orders.py
galapy_core/portfolio.py
galapy_core/generators/README.md
galapy_core/generators/__init__.py
galapy_core/generators/price.py
galapy_core/oms/__init__.py
galapy_core/oms/database_manager.py
galapy_core/oms/exchange_api.py
galapy_core/oms/order_manager.py
galapy_core-0.3.0.dist-info/METADATA
galapy_core-0.3.0.dist-info/WHEEL
galapy_core-0.3.0.dist-info/RECORD
